puck_me/game/game.py
puck_me/goalie/goalie.py
puck_me/goalie/goalie_game.py
puck_me/goalies.py
puck_me/hock_ref.py
puck_me/lib/split_types.py
puck_me/lib/utils.py
puck_me/player/player.py
puck_me/players.py
puck_me/skater/skater.py
puck_me/skater/skater_game.py
puck_me/skaters.py
puck_me-0.3.0.dist-info/WHEEL
puck_me-0.3.0.dist-info/METADATA
puck_me-0.3.0.dist-info/RECORD
